module_inspector/__init__.py
module_inspector/inspector.py
module_inspector-0.2.0.dist-info/LICENSE
module_inspector-0.2.0.dist-info/METADATA
module_inspector-0.2.0.dist-info/WHEEL
module_inspector-0.2.0.dist-info/top_level.txt
module_inspector-0.2.0.dist-info/RECORD
