Metadata-Version: 2.1
Name: module-inspector
Version: 0.2.0
Summary: A utility package to inspect imported packages and their aliases.
Home-page: https://github.com/ntluong95/module-inspector
Author: Luong Nguyen Thanh
Author-email: Luong Nguyen Thanh <ph.ntluong95@gmail.com>
Project-URL: Homepage, https://github.com/ntluong95/module-inspector
Project-URL: Issues, https://github.com/ntluong95/module-inspector/issues
Classifier: Programming Language :: Python :: 3
Classifier: Operating System :: OS Independent
Requires-Python: >=3.6
License-File: LICENSE
